cmdcraft/__init__.py
cmdcraft/base.py
cmdcraft/command.py
cmdcraft/completer.py
cmdcraft/input.py
cmdcraft/parameter.py
cmdcraft/prompter.py
cmdcraft-0.0.6.dist-info/LICENSE
cmdcraft-0.0.6.dist-info/METADATA
cmdcraft-0.0.6.dist-info/WHEEL
cmdcraft-0.0.6.dist-info/top_level.txt
cmdcraft-0.0.6.dist-info/RECORD
