Metadata-Version: 2.1
Name: cmdcraft
Version: 0.0.6
Home-page: https://github.com/weinsen/cmdcraft
Author: A. M. Weinsen Jr.
Classifier: Development Status :: 2 - Pre-Alpha
Classifier: Intended Audience :: Developers
Classifier: Intended Audience :: System Administrators
Classifier: License :: OSI Approved :: BSD License
Classifier: Operating System :: OS Independent
Classifier: Programming Language :: Python :: 3
Classifier: Programming Language :: Python :: 3.10
Classifier: Programming Language :: Python :: 3.11
Classifier: Programming Language :: Python :: 3.12
Classifier: Programming Language :: Python :: 3 :: Only
Classifier: Programming Language :: Python
Classifier: Topic :: Software Development
Requires-Python: >=3.10.0
License-File: LICENSE
Requires-Dist: prompt_toolkit
Provides-Extra: dev
Requires-Dist: ruff; extra == "dev"
Requires-Dist: pytest; extra == "dev"
